[ {
  "carId" : "8085a839-8601-4e41-96f9-3da12e0a0ba8",
  "regNumber" : "AHT444",
  "brand" : "Tesla",
  "model" : " t40",
  "regDate" : "2019-01-01",
  "owner" : {
    "ownerId" : "40f7da7a-bce7-4f26-b99e-6c94741ff8b8",
    "name" : "Hala",
    "birthDate" : [ 1985, 12, 24 ]
  }
}, {
  "carId" : "065b621a-8dad-4f9f-b0a4-a9cc3cfb6d04",
  "regNumber" : "DTD555",
  "brand" : "Citron",
  "model" : "c67",
  "regDate" : "2018-02-02",
  "owner" : {
    "ownerId" : "e540b0ce-804e-426d-8985-90adb3023bf0",
    "name" : "Khalifa",
    "birthDate" : [ 1977, 3, 18 ]
  }
}, {
  "carId" : "49512f20-4751-422c-b37d-767cb600e92c",
  "regNumber" : "YRT123",
  "brand" : "Volvo",
  "model" : "xc90",
  "regDate" : "2019-12-20",
  "owner" : {
    "ownerId" : "e540b0ce-804e-426d-8985-90adb3023bf0",
    "name" : "Khalifa",
    "birthDate" : [ 1977, 3, 18 ]
  }
} ]